uplot/__init__.py
uplt/__init__.py
uplt/color.py
uplt/default.py
uplt/detect.py
uplt/interface.py
uplt/plot.py
uplt/utype.py
uplt/engine/MatplotEngine.py
uplt/engine/MatplotFigure.py
uplt/engine/PlotlyEngine5.py
uplt/engine/PlotlyFigure5.py
uplt/engine/__init__.py
uplt/engine/manage.py
uplt/engine/matplot/plot.py
uplt/engine/plotly/axis_range.py
uplt/engine/plotly/mapping.py
uplt/engine/plotly/plot.py
uplt/engine/plotly/scale.py
uplt/engine/style/plotly.py
uplt/plugin/IPlotPlugin.py
uplt/plugin/__init__.py
uplt/plugin/manage.py
uplt/utool/__init__.py
uplt/utool/grid.py
uplt/utool/image.py
uplt/utool/param.py
uplt_py-0.9.1.dist-info/METADATA
uplt_py-0.9.1.dist-info/WHEEL
uplt_py-0.9.1.dist-info/licenses/LICENSE
uplt_py-0.9.1.dist-info/RECORD
