Metadata-Version: 2.4
Name: uplt-py
Version: 0.9.1
Summary: Unified API and style for Python plotting libraries
Project-URL: Repository, https://github.com/makarovdi/uplt
Project-URL: Issues, https://github.com/makarovdi/uplt/issues
Project-URL: Changelog, https://github.com/makarovdi/uplt/blob/main/CHANGELOG.md
Author-email: Dmitry Makarov <makarovdmv@gmail.com>
License-Expression: BSD-3-Clause
License-File: LICENSE
Classifier: Intended Audience :: Developers
Classifier: Intended Audience :: Science/Research
Classifier: Operating System :: OS Independent
Classifier: Programming Language :: Python :: 3
Classifier: Topic :: Scientific/Engineering :: Visualization
Requires-Python: >=3.10
Requires-Dist: numpy<3.0,>=1.21
Requires-Dist: pillow>=11.3
Requires-Dist: scipy<2.0,>=1.11
Requires-Dist: typing-extensions<5.0,>=4.15
Provides-Extra: all
Requires-Dist: kaleido<2.0,>=0.4; extra == 'all'
Requires-Dist: matplotlib<4.0,>=3.7; extra == 'all'
Requires-Dist: plotly<7.0,>=5.16; extra == 'all'
Provides-Extra: matplot
Requires-Dist: matplotlib<4.0,>=3.7; extra == 'matplot'
Provides-Extra: plotly
Requires-Dist: kaleido<2.0,>=0.4; extra == 'plotly'
Requires-Dist: plotly<7.0,>=5.16; extra == 'plotly'
